tigo_mcp_server/__init__.py
tigo_mcp_server/__main__.py
tigo_mcp_server/py.typed
tigo_mcp_server/server.py
tigo_mcp_server-0.2.0.dist-info/METADATA
tigo_mcp_server-0.2.0.dist-info/WHEEL
tigo_mcp_server-0.2.0.dist-info/entry_points.txt
tigo_mcp_server-0.2.0.dist-info/licenses/LICENSE
tigo_mcp_server-0.2.0.dist-info/RECORD
