Metadata-Version: 2.4
Name: tigo-mcp-server
Version: 0.2.0
Summary: Model Context Protocol server for Tigo Energy solar system monitoring and analytics
Project-URL: Homepage, https://github.com/matt-dreyer/Tigo_MCP_server
Project-URL: Repository, https://github.com/matt-dreyer/Tigo_MCP_server
Project-URL: Documentation, https://github.com/matt-dreyer/Tigo_MCP_server#readme
Project-URL: Issues, https://github.com/matt-dreyer/Tigo_MCP_server/issues
Project-URL: Changelog, https://github.com/matt-dreyer/Tigo_MCP_server/blob/main/CHANGELOG.md
Author-email: Matt Dreyer <matt_dreyer@hotmail.com>
Maintainer-email: Matt Dreyer <matt_dreyer@hotmail.com>
License: MIT License
License-File: LICENSE
Keywords: ai-tools,claude,energy,llm,mcp,model-context-protocol,monitoring,photovoltaic,renewable-energy,solar,tigo
Classifier: Development Status :: 4 - Beta
Classifier: Environment :: Console
Classifier: Framework :: AsyncIO
Classifier: Intended Audience :: Developers
Classifier: Intended Audience :: System Administrators
Classifier: License :: OSI Approved :: MIT License
Classifier: Operating System :: OS Independent
Classifier: Programming Language :: Python :: 3
Classifier: Programming Language :: Python :: 3.10
Classifier: Programming Language :: Python :: 3.11
Classifier: Programming Language :: Python :: 3.12
Classifier: Topic :: Home Automation
Classifier: Topic :: Internet :: WWW/HTTP :: Dynamic Content
Classifier: Topic :: Scientific/Engineering
Classifier: Topic :: Software Development :: Libraries :: Python Modules
Classifier: Topic :: System :: Monitoring
Requires-Python: >=3.10
Requires-Dist: fastmcp>=2.0.0
Requires-Dist: mcp>=0.9.0
Requires-Dist: python-dotenv>=1.0.0
Requires-Dist: tigo-python>=0.2.0
Provides-Extra: dev
Requires-Dist: black>=23.0.0; extra == 'dev'
Requires-Dist: build>=0.10.0; extra == 'dev'
Requires-Dist: flake8>=6.0.0; extra == 'dev'
Requires-Dist: mypy>=1.0.0; extra == 'dev'
Requires-Dist: pytest-asyncio>=0.21.0; extra == 'dev'
Requires-Dist: pytest-cov>=4.0.0; extra == 'dev'
Requires-Dist: pytest>=7.0.0; extra == 'dev'
Requires-Dist: twine>=4.0.0; extra == 'dev'
Provides-Extra: test
Requires-Dist: pytest-asyncio>=0.21.0; extra == 'test'
Requires-Dist: pytest-cov>=4.0.0; extra == 'test'
Requires-Dist: pytest-mock>=3.10.0; extra == 'test'
Requires-Dist: pytest>=7.0.0; extra == 'test'
